curve2vec/__init__.py
curve2vec/embeddings/__init__.py
curve2vec/embeddings/fourier.py
curve2vec/utils/__init__.py
curve2vec/utils/data.py
curve2vec/utils/visualization.py
curve2vec-0.1.5.dist-info/LICENSE
curve2vec-0.1.5.dist-info/METADATA
curve2vec-0.1.5.dist-info/WHEEL
curve2vec-0.1.5.dist-info/top_level.txt
curve2vec-0.1.5.dist-info/RECORD
