Metadata-Version: 2.1
Name: curve2vec
Version: 0.1.5
Summary: A Python package for generating vector embeddings of curves
Author-email: Daniel Cieśliński <daniel98c@gmail.com>
Project-URL: Homepage, https://github.com/danielcieslinski/curve2vec
Project-URL: Bug Tracker, https://github.com/danielcieslinski/curve2vec/issues
Keywords: curve,embedding,representation,vector
Classifier: Development Status :: 3 - Alpha
Classifier: Intended Audience :: Developers
Classifier: Topic :: Software Development :: Libraries
Classifier: License :: OSI Approved :: MIT License
Classifier: Programming Language :: Python :: 3.7
Classifier: Programming Language :: Python :: 3.8
Classifier: Programming Language :: Python :: 3.9
Classifier: Programming Language :: Python :: 3.10
License-File: LICENSE
